{"compressionlevel":-1,"height":96,"infinite":false,"layers":[{"id":2,"image":"../background/4ab0af106332567.5f91416c61956.jpg","name":"background","opacity":1,"type":"imagelayer","visible":true,"x":0,"y":0},{"draworder":"index","id":3,"name":"game-board","objects":[{"gid":146,"height":231,"id":1,"name":"","properties":[{"name":"addon","type":"string","value":""},{"name":"addonValue","type":"int","value":-1},{"name":"faceUp","type":"bool","value":false},{"name":"suit","type":"int","value":-1},{"name":"type","type":"string","value":"value"},{"name":"value","type":"int","value":-1}],"rotation":0,"type":"","visible":true,"width":162,"x":539.714285714286,"y":734},{"gid":146,"height":231,"id":2,"name":"","properties":[{"name":"addon","type":"string","value":""},{"name":"addonValue","type":"int","value":-1},{"name":"faceUp","type":"bool","value":false},{"name":"suit","type":"int","value":-1},{"name":"type","type":"string","value":"value"},{"name":"value","type":"int","value":-1}],"rotation":0,"type":"","visible":true,"width":162,"x":435.142857142857,"y":583},{"gid":146,"height":231,"id":3,"name":"","properties":[{"name":"addon","type":"string","value":""},{"name":"addonValue","type":"int","value":-1},{"name":"faceUp","type":"bool","value":false},{"name":"suit","type":"int","value":-1},{"name":"type","type":"string","value":"value"},{"name":"value","type":"int","value":-1}],"rotation":60.0000000000001,"type":"","visible":true,"width":162,"x":350,"y":832},{"gid":146,"height":231,"id":4,"name":"","properties":[{"name":"addon","type":"string","value":""},{"name":"addonValue","type":"int","value":-1},{"name":"faceUp","type":"bool","value":false},{"name":"suit","type":"int","value":-1},{"name":"type","type":"string","value":"value"},{"name":"value","type":"int","value":-1}],"rotation":300,"type":"","visible":true,"width":162,"x":730,"y":832},{"gid":146,"height":231,"id":5,"name":"","properties":[{"name":"addon","type":"string","value":""},{"name":"addonValue","type":"int","value":-1},{"name":"faceUp","type":"bool","value":false},{"name":"suit","type":"int","value":-1},{"name":"type","type":"string","value":"value"},{"name":"value","type":"int","value":-1}],"rotation":0,"type":"","visible":true,"width":162,"x":641,"y":583},{"gid":153,"height":231,"id":6,"name":"","properties":[{"name":"addon","type":"string","value":""},{"name":"addonValue","type":"int","value":-1},{"name":"faceUp","type":"bool","value":false},{"name":"suit","type":"int","value":-1},{"name":"type","type":"string","value":"mysterious"},{"name":"value","type":"int","value":-1}],"rotation":9.999991245618,"type":"","visible":true,"width":162,"x":423.571428571428,"y":506},{"gid":146,"height":231,"id":7,"name":"","properties":[{"name":"addon","type":"string","value":""},{"name":"addonValue","type":"int","value":-1},{"name":"faceUp","type":"bool","value":false},{"name":"suit","type":"int","value":-1},{"name":"type","type":"string","value":"value"},{"name":"value","type":"int","value":-1}],"rotation":-9.999991245618,"type":"","visible":true,"width":162,"x":652.571428571428,"y":506},{"gid":146,"height":231,"id":8,"name":"","properties":[{"name":"addon","type":"string","value":""},{"name":"addonValue","type":"int","value":-1},{"name":"faceUp","type":"bool","value":false},{"name":"suit","type":"int","value":-1},{"name":"type","type":"string","value":"value"},{"name":"value","type":"int","value":-1}],"rotation":5.000008754382,"type":"","visible":true,"width":162,"x":250,"y":832},{"gid":153,"height":231,"id":9,"name":"","properties":[{"name":"addon","type":"string","value":""},{"name":"addonValue","type":"int","value":-1},{"name":"faceUp","type":"bool","value":false},{"name":"suit","type":"int","value":-1},{"name":"type","type":"string","value":"mysterious"},{"name":"value","type":"int","value":-1}],"rotation":-5,"type":"","visible":true,"width":162,"x":840,"y":832},{"gid":146,"height":231,"id":10,"name":"","properties":[{"name":"addon","type":"string","value":""},{"name":"addonValue","type":"int","value":-1},{"name":"faceUp","type":"bool","value":false},{"name":"suit","type":"int","value":-1},{"name":"type","type":"string","value":"value"},{"name":"value","type":"int","value":-1}],"rotation":39.99999706812,"type":"","visible":true,"width":162,"x":725.28571428571,"y":1105},{"gid":146,"height":231,"id":11,"name":"","properties":[{"name":"addon","type":"string","value":""},{"name":"addonValue","type":"int","value":-1},{"name":"faceUp","type":"bool","value":false},{"name":"suit","type":"int","value":-1},{"name":"type","type":"string","value":"value"},{"name":"value","type":"int","value":-1}],"rotation":-39.99999706812,"type":"","visible":true,"width":162,"x":355,"y":1105},{"gid":146,"height":231,"id":12,"name":"","properties":[{"name":"addon","type":"string","value":""},{"name":"addonValue","type":"int","value":-1},{"name":"faceUp","type":"bool","value":false},{"name":"suit","type":"int","value":-1},{"name":"type","type":"string","value":"value"},{"name":"value","type":"int","value":-1}],"rotation":-39.99999706812,"type":"","visible":true,"width":162,"x":725.28571428571,"y":1381},{"gid":146,"height":231,"id":13,"name":"","properties":[{"name":"addon","type":"string","value":""},{"name":"addonValue","type":"int","value":-1},{"name":"faceUp","type":"bool","value":false},{"name":"suit","type":"int","value":-1},{"name":"type","type":"string","value":"value"},{"name":"value","type":"int","value":-1}],"rotation":39.99999706812,"type":"","visible":true,"width":162,"x":355,"y":1381},{"gid":146,"height":231,"id":14,"name":"","properties":[{"name":"addon","type":"string","value":""},{"name":"addonValue","type":"int","value":-1},{"name":"faceUp","type":"bool","value":false},{"name":"suit","type":"int","value":-1},{"name":"type","type":"string","value":"value"},{"name":"value","type":"int","value":-1}],"rotation":9.999991245618,"type":"","visible":true,"width":162,"x":354.142857142857,"y":572},{"gid":146,"height":231,"id":15,"name":"","properties":[{"name":"addon","type":"string","value":""},{"name":"addonValue","type":"int","value":-1},{"name":"faceUp","type":"bool","value":false},{"name":"suit","type":"int","value":-1},{"name":"type","type":"string","value":"value"},{"name":"value","type":"int","value":-1}],"rotation":-9.999991245618,"type":"","visible":true,"width":162,"x":722,"y":572},{"gid":146,"height":231,"id":16,"name":"","properties":[{"name":"addon","type":"string","value":""},{"name":"addonValue","type":"int","value":-1},{"name":"faceUp","type":"bool","value":false},{"name":"suit","type":"int","value":-1},{"name":"type","type":"string","value":"value"},{"name":"value","type":"int","value":-1}],"rotation":5.000008754382,"type":"","visible":true,"width":162,"x":140,"y":742},{"gid":146,"height":231,"id":17,"name":"","properties":[{"name":"addon","type":"string","value":""},{"name":"addonValue","type":"int","value":-1},{"name":"faceUp","type":"bool","value":false},{"name":"suit","type":"int","value":-1},{"name":"type","type":"string","value":"value"},{"name":"value","type":"int","value":-1}],"rotation":-5,"type":"","visible":true,"width":162,"x":940,"y":742},{"gid":146,"height":231,"id":18,"name":"","properties":[{"name":"addon","type":"string","value":""},{"name":"addonValue","type":"int","value":-1},{"name":"faceUp","type":"bool","value":false},{"name":"suit","type":"int","value":-1},{"name":"type","type":"string","value":"value"},{"name":"value","type":"int","value":-1}],"rotation":0.00000768847199950073,"type":"","visible":true,"width":162,"x":150,"y":902},{"gid":146,"height":231,"id":19,"name":"","properties":[{"name":"addon","type":"string","value":""},{"name":"addonValue","type":"int","value":-1},{"name":"faceUp","type":"bool","value":false},{"name":"suit","type":"int","value":-1},{"name":"type","type":"string","value":"value"},{"name":"value","type":"int","value":-1}],"rotation":0,"type":"","visible":true,"width":162,"x":930,"y":902},{"gid":146,"height":231,"id":20,"name":"","properties":[{"name":"addon","type":"string","value":""},{"name":"addonValue","type":"int","value":-1},{"name":"faceUp","type":"bool","value":false},{"name":"suit","type":"int","value":-1},{"name":"type","type":"string","value":"value"},{"name":"value","type":"int","value":-1}],"rotation":14.999992311528,"type":"","visible":true,"width":162,"x":331,"y":506},{"gid":146,"height":231,"id":21,"name":"","properties":[{"name":"addon","type":"string","value":""},{"name":"addonValue","type":"int","value":-1},{"name":"faceUp","type":"bool","value":false},{"name":"suit","type":"int","value":-1},{"name":"type","type":"string","value":"value"},{"name":"value","type":"int","value":-1}],"rotation":-14.999992311528,"type":"","visible":true,"width":162,"x":745.142857142857,"y":506},{"gid":146,"height":231,"id":22,"name":"","properties":[{"name":"addon","type":"string","value":""},{"name":"addonValue","type":"int","value":-1},{"name":"faceUp","type":"bool","value":false},{"name":"suit","type":"int","value":-1},{"name":"type","type":"string","value":"value"},{"name":"value","type":"int","value":-1}],"rotation":0,"type":"","visible":true,"width":162,"x":540.14285714286,"y":1061},{"gid":153,"height":231,"id":23,"name":"","properties":[{"name":"addon","type":"string","value":""},{"name":"addonValue","type":"int","value":-1},{"name":"faceUp","type":"bool","value":false},{"name":"suit","type":"int","value":-1},{"name":"type","type":"string","value":"mysterious"},{"name":"value","type":"int","value":-1}],"rotation":0,"type":"","visible":true,"width":162,"x":320,"y":1241},{"gid":146,"height":231,"id":24,"name":"","properties":[{"name":"addon","type":"string","value":""},{"name":"addonValue","type":"int","value":-1},{"name":"faceUp","type":"bool","value":false},{"name":"suit","type":"int","value":-1},{"name":"type","type":"string","value":"value"},{"name":"value","type":"int","value":-1}],"rotation":0,"type":"","visible":true,"width":162,"x":540.14285714286,"y":1414},{"gid":153,"height":231,"id":25,"name":"","properties":[{"name":"addon","type":"string","value":""},{"name":"addonValue","type":"int","value":-1},{"name":"faceUp","type":"bool","value":false},{"name":"suit","type":"int","value":-1},{"name":"type","type":"string","value":"mysterious"},{"name":"value","type":"int","value":-1}],"rotation":0,"type":"","visible":true,"width":162,"x":748.14285714286,"y":1241},{"gid":146,"height":231,"id":26,"name":"","properties":[{"name":"addon","type":"string","value":""},{"name":"addonValue","type":"int","value":-1},{"name":"faceUp","type":"bool","value":false},{"name":"suit","type":"int","value":-1},{"name":"type","type":"string","value":"value"},{"name":"value","type":"int","value":-1}],"rotation":34.999998867,"type":"","visible":true,"width":162,"x":690.57142857143,"y":1061},{"gid":146,"height":231,"id":27,"name":"","properties":[{"name":"addon","type":"string","value":""},{"name":"addonValue","type":"int","value":-1},{"name":"faceUp","type":"bool","value":false},{"name":"suit","type":"int","value":-1},{"name":"type","type":"string","value":"value"},{"name":"value","type":"int","value":-1}],"rotation":-34.999998867,"type":"","visible":true,"width":162,"x":378.14285714286,"y":1061},{"gid":146,"height":231,"id":28,"name":"","properties":[{"name":"addon","type":"string","value":""},{"name":"addonValue","type":"int","value":-1},{"name":"faceUp","type":"bool","value":false},{"name":"suit","type":"int","value":-1},{"name":"type","type":"string","value":"value"},{"name":"value","type":"int","value":-1}],"rotation":34.999998867,"type":"","visible":true,"width":162,"x":378.14285714286,"y":1414},{"gid":146,"height":231,"id":29,"name":"","properties":[{"name":"addon","type":"string","value":""},{"name":"addonValue","type":"int","value":-1},{"name":"faceUp","type":"bool","value":false},{"name":"suit","type":"int","value":-1},{"name":"type","type":"string","value":"value"},{"name":"value","type":"int","value":-1}],"rotation":-34.999998867,"type":"","visible":true,"width":162,"x":690.57142857143,"y":1414},{"gid":146,"height":231,"id":30,"name":"","properties":[{"name":"addon","type":"string","value":""},{"name":"addonValue","type":"int","value":-1},{"name":"faceUp","type":"bool","value":false},{"name":"suit","type":"int","value":-1},{"name":"type","type":"string","value":"value"},{"name":"value","type":"int","value":-1}],"rotation":0,"type":"","visible":true,"width":162,"x":412.57142857143,"y":1241},{"gid":146,"height":231,"id":31,"name":"","properties":[{"name":"addon","type":"string","value":""},{"name":"addonValue","type":"int","value":-1},{"name":"faceUp","type":"bool","value":false},{"name":"suit","type":"int","value":-1},{"name":"type","type":"string","value":"value"},{"name":"value","type":"int","value":-1}],"rotation":0,"type":"","visible":true,"width":162,"x":667.14285714286,"y":1241},{"gid":146,"height":231,"id":32,"name":"","properties":[{"name":"addon","type":"string","value":""},{"name":"addonValue","type":"int","value":-1},{"name":"faceUp","type":"bool","value":false},{"name":"suit","type":"int","value":-1},{"name":"type","type":"string","value":"value"},{"name":"value","type":"int","value":-1}],"rotation":0,"type":"","visible":true,"width":162,"x":540.14285714286,"y":1094},{"gid":146,"height":231,"id":33,"name":"","properties":[{"name":"addon","type":"string","value":""},{"name":"addonValue","type":"int","value":-1},{"name":"faceUp","type":"bool","value":false},{"name":"suit","type":"int","value":-1},{"name":"type","type":"string","value":"value"},{"name":"value","type":"int","value":-1}],"rotation":0,"type":"","visible":true,"width":162,"x":540.14285714286,"y":1381}],"opacity":1,"type":"objectgroup","visible":true,"x":0,"y":0},{"draworder":"index","id":4,"name":"settings","objects":[{"gid":146,"height":231,"id":1,"name":"","properties":[{"name":"addon","type":"string","value":""},{"name":"addonValue","type":"int","value":-1},{"name":"faceUp","type":"bool","value":false},{"name":"random","type":"bool","value":true},{"name":"suit","type":"int","value":-1},{"name":"type","type":"string","value":"value"},{"name":"value","type":"int","value":-1}],"rotation":0,"type":"","visible":true,"width":162,"x":240,"y":1680},{"gid":146,"height":231,"id":2,"name":"","properties":[{"name":"addon","type":"string","value":""},{"name":"addonValue","type":"int","value":-1},{"name":"faceUp","type":"bool","value":false},{"name":"random","type":"bool","value":true},{"name":"suit","type":"int","value":-1},{"name":"type","type":"string","value":"value"},{"name":"value","type":"int","value":-1}],"rotation":0,"type":"","visible":true,"width":162,"x":260,"y":1680},{"gid":146,"height":231,"id":3,"name":"","properties":[{"name":"addon","type":"string","value":""},{"name":"addonValue","type":"int","value":-1},{"name":"faceUp","type":"bool","value":false},{"name":"random","type":"bool","value":true},{"name":"suit","type":"int","value":-1},{"name":"type","type":"string","value":"value"},{"name":"value","type":"int","value":-1}],"rotation":0,"type":"","visible":true,"width":162,"x":280,"y":1680},{"gid":146,"height":231,"id":4,"name":"","properties":[{"name":"addon","type":"string","value":""},{"name":"addonValue","type":"int","value":-1},{"name":"faceUp","type":"bool","value":false},{"name":"random","type":"bool","value":true},{"name":"suit","type":"int","value":-1},{"name":"type","type":"string","value":"value"},{"name":"value","type":"int","value":-1}],"rotation":0,"type":"","visible":true,"width":162,"x":300,"y":1680},{"gid":146,"height":231,"id":5,"name":"","properties":[{"name":"addon","type":"string","value":""},{"name":"addonValue","type":"int","value":-1},{"name":"faceUp","type":"bool","value":false},{"name":"random","type":"bool","value":true},{"name":"suit","type":"int","value":-1},{"name":"type","type":"string","value":"value"},{"name":"value","type":"int","value":-1}],"rotation":0,"type":"","visible":true,"width":162,"x":320,"y":1680},{"gid":146,"height":231,"id":6,"name":"","properties":[{"name":"addon","type":"string","value":""},{"name":"addonValue","type":"int","value":-1},{"name":"faceUp","type":"bool","value":false},{"name":"random","type":"bool","value":true},{"name":"suit","type":"int","value":-1},{"name":"type","type":"string","value":"value"},{"name":"value","type":"int","value":-1}],"rotation":0,"type":"","visible":true,"width":162,"x":340,"y":1680},{"gid":146,"height":231,"id":7,"name":"","properties":[{"name":"addon","type":"string","value":""},{"name":"addonValue","type":"int","value":-1},{"name":"faceUp","type":"bool","value":false},{"name":"random","type":"bool","value":true},{"name":"suit","type":"int","value":-1},{"name":"type","type":"string","value":"value"},{"name":"value","type":"int","value":-1}],"rotation":0,"type":"","visible":true,"width":162,"x":360,"y":1680},{"gid":146,"height":231,"id":8,"name":"","properties":[{"name":"addon","type":"string","value":""},{"name":"addonValue","type":"int","value":-1},{"name":"faceUp","type":"bool","value":false},{"name":"random","type":"bool","value":true},{"name":"suit","type":"int","value":-1},{"name":"type","type":"string","value":"value"},{"name":"value","type":"int","value":-1}],"rotation":0,"type":"","visible":true,"width":162,"x":380,"y":1680},{"gid":146,"height":231,"id":9,"name":"","properties":[{"name":"addon","type":"string","value":""},{"name":"addonValue","type":"int","value":-1},{"name":"faceUp","type":"bool","value":false},{"name":"random","type":"bool","value":true},{"name":"suit","type":"int","value":-1},{"name":"type","type":"string","value":"value"},{"name":"value","type":"int","value":-1}],"rotation":0,"type":"","visible":true,"width":162,"x":400,"y":1680},{"gid":146,"height":231,"id":10,"name":"","properties":[{"name":"addon","type":"string","value":""},{"name":"addonValue","type":"int","value":-1},{"name":"faceUp","type":"bool","value":false},{"name":"random","type":"bool","value":true},{"name":"suit","type":"int","value":-1},{"name":"type","type":"string","value":"value"},{"name":"value","type":"int","value":-1}],"rotation":0,"type":"","visible":true,"width":162,"x":420,"y":1680},{"gid":146,"height":231,"id":11,"name":"","properties":[{"name":"addon","type":"string","value":""},{"name":"addonValue","type":"int","value":-1},{"name":"faceUp","type":"bool","value":false},{"name":"random","type":"bool","value":true},{"name":"suit","type":"int","value":-1},{"name":"type","type":"string","value":"value"},{"name":"value","type":"int","value":-1}],"rotation":0,"type":"","visible":true,"width":162,"x":440,"y":1680},{"gid":146,"height":231,"id":12,"name":"","properties":[{"name":"addon","type":"string","value":""},{"name":"addonValue","type":"int","value":-1},{"name":"faceUp","type":"bool","value":false},{"name":"random","type":"bool","value":true},{"name":"suit","type":"int","value":-1},{"name":"type","type":"string","value":"value"},{"name":"value","type":"int","value":-1}],"rotation":0,"type":"","visible":true,"width":162,"x":460,"y":1680},{"gid":146,"height":231,"id":13,"name":"","properties":[{"name":"addon","type":"string","value":""},{"name":"addonValue","type":"int","value":-1},{"name":"faceUp","type":"bool","value":false},{"name":"random","type":"bool","value":true},{"name":"suit","type":"int","value":-1},{"name":"type","type":"string","value":"value"},{"name":"value","type":"int","value":-1}],"rotation":0,"type":"","visible":true,"width":162,"x":480,"y":1680},{"gid":146,"height":231,"id":14,"name":"","properties":[{"name":"addon","type":"string","value":""},{"name":"addonValue","type":"int","value":-1},{"name":"faceUp","type":"bool","value":false},{"name":"random","type":"bool","value":true},{"name":"suit","type":"int","value":-1},{"name":"type","type":"string","value":"value"},{"name":"value","type":"int","value":-1}],"rotation":0,"type":"","visible":true,"width":162,"x":500,"y":1680}],"opacity":1,"properties":[{"name":"star_1","type":"int","value":0},{"name":"star_2","type":"int","value":0},{"name":"star_3","type":"string","value":"-1, 0, -1, 50, 1"}],"type":"objectgroup","visible":true,"x":0,"y":0},{"draworder":"index","id":5,"name":"code-breakers","objects":[],"opacity":1,"properties":[{"name":"direction","type":"string","value":"left"}],"type":"objectgroup","visible":true,"x":0,"y":0}],"nextlayerid":8,"nextobjectid":66,"orientation":"orthogonal","renderorder":"right-down","tiledversion":"1.10.1","tileheight":20,"tilesets":[{"firstgid":1,"source":"../Cards.tsx"},{"firstgid":156,"source":"../CodeBreakers.tsx"}],"tilewidth":20,"type":"map","version":"1.10","width":54}